{"upload_date": "20130116", "creator": null, "series": null, "height": 1080, "like_count": 381, "duration": 6, "fulltitle": "TESTUPLOAD! Sexy new Intro is sexy! :D", "playlist_index": 426, "view_count": 32058, "playlist": "LeNEWS", "title": "TESTUPLOAD! Sexy new Intro is sexy! :D", "_filename": "426-WfSVk44K06s-TESTUPLOAD_Sexy_new_Intro_is_sexy_-D.mp4", "tags": ["LeFloid", "LeNEWS", "nerdgasm", "sexy", "intro", "TESTUPLOAD", "nicht", "gelistet", "Mediakraft"], "is_live": null, "id": "WfSVk44K06s", "dislike_count": 3, "average_rating": 4.96875, "abr": 128, "uploader_url": "http://www.youtube.com/user/LeFloid", "categories": ["Entertainment"], "fps": 25, "stretched_ratio": null, "season_number": null, "annotations": null, "webpage_url_basename": "WfSVk44K06s", "acodec": "vorbis", "display_id": "WfSVk44K06s", "automatic_captions": {}, "description": "Floid auf Facebook: http://www.facebook.com/lefloidfans\n\nFloid auf YouTube: http://www.youtube.com/lefloid\n\nZweiter Kanal: http://www.youtube.com/flipfloid\n\nGaming-Kanal: http://www.youtube.com/lefloidgames\n\nPost geht an:\n\nLeFloid\nPostfach 021066\n10122 Berlin\n\nSo Jungs und meine sehr verehrten M\u00e4dels! :P\nTDHUDGAS! (f\u00fcr alle, die neu sind: Teilen Daumen Hoch Und Der Ganze Andere Schei\u00df :P)\n\nIch w\u00fcnsche euch eine traumhafte Woche und freue mich auf's n\u00e4chste Mal! Bis bald!\n\n--------", "format": "137 - 1920x1080 (DASH video)+171 - audio only (DASH audio)", "start_time": null, "formats": [{"asr": 44100, "tbr": 128, "protocol": "https", "format": "140 - audio only (DASH audio)", "format_note": "DASH audio", "height": null, "preference": -50, "manifest_url": "https://manifest.googlevideo.com/api/manifest/dash/expire/1492545785/pl/16/as/fmp4_audio_clear%2Cfmp4_sd_hd_clear/ei/mRz2WI-5IIGncLCDhNAP/id/o-AJfpOJIZRd4guGqLVZo5YFEVFfZIbjjwJLEK85KKX_CK/upn/56r6CoC9ww0/initcwndbps/7396250/sparams/as%2Cei%2Chfr%2Cid%2Cinitcwndbps%2Cip%2Cipbits%2Citag%2Cmm%2Cmn%2Cms%2Cmv%2Cpl%2Cplayback_host%2Crequiressl%2Csource%2Cexpire/ip/138.232.125.82/signature/E43235ACE6B2AD6546BC00213957D21D96561B67.CED53CE71D11AD2C16E24BA0236F96C4CCE98958/source/youtube/ms/au/playback_host/r1---sn-5jvoxu-8pxe.googlevideo.com/mt/1492524097/mv/m/mm/31/mn/sn-5jvoxu-8pxe/requiressl/yes/key/yt6/itag/0/ipbits/0/hfr/1", "format_id": "140", "container": "m4a_dash", "language": null, "http_headers": {"Accept-Charset": "ISO-8859-1,utf-8;q=0.7,*;q=0.7", "Accept-Language": "en-us,en;q=0.5", "Accept-Encoding": "gzip, deflate", "Accept": "text/html,application/xhtml+xml,application/xml;q=0.9,*/*;q=0.8", "User-Agent": "Mozilla/5.0 (X11; Linux x86_64; rv:10.0) Gecko/20150101 Firefox/47.0 (Chrome)"}, "url": "https://r1---sn-5jvoxu-8pxe.googlevideo.com/videoplayback?id=59f495938e0ad3ab&itag=140&source=youtube&requiressl=yes&pl=16&ei=mRz2WI-5IIGncLCDhNAP&initcwndbps=7396250&ms=au&mv=m&mm=31&mn=sn-5jvoxu-8pxe&ratebypass=yes&mime=audio/mp4&gir=yes&clen=89196&lmt=1388018120449577&dur=5.572&upn=56r6CoC9ww0&signature=28452A78C8320012A085B477616B0DDE4076F993.4C18DDE89B371A1533DC06BD89F857943C100808&mt=1492524097&key=dg_yt0&ip=138.232.125.82&ipbits=0&expire=1492545785&sparams=ip,ipbits,expire,id,itag,source,requiressl,pl,ei,initcwndbps,ms,mv,mm,mn,ratebypass,mime,gir,clen,lmt,dur", "vcodec": "none", "ext": "m4a", "width": null, "abr": 128, "filesize": 89196, "fps": null, "acodec": "mp4a.40.2"}, {"http_headers": {"Accept-Charset": "ISO-8859-1,utf-8;q=0.7,*;q=0.7", "Accept-Language": "en-us,en;q=0.5", "Accept-Encoding": "gzip, deflate", "Accept": "text/html,application/xhtml+xml,application/xml;q=0.9,*/*;q=0.8", "User-Agent": "Mozilla/5.0 (X11; Linux x86_64; rv:10.0) Gecko/20150101 Firefox/47.0 (Chrome)"}, "tbr": 134.528, "protocol": "https", "format": "171 - audio only (DASH audio)", "url": "https://r1---sn-5jvoxu-8pxe.googlevideo.com/videoplayback?mime=audio%2Fwebm&ip=138.232.125.82&requiressl=yes&mm=31&source=youtube&pl=16&mn=sn-5jvoxu-8pxe&ipbits=0&mt=1492524097&mv=m&id=o-APL3vFNNdf9glAigF87X04wArd6xkPg5cmajUkNlumu3&ms=au&expire=1492545785&gir=yes&sparams=clen%2Cdur%2Cei%2Cgir%2Cid%2Cinitcwndbps%2Cip%2Cipbits%2Citag%2Ckeepalive%2Clmt%2Cmime%2Cmm%2Cmn%2Cms%2Cmv%2Cpl%2Crequiressl%2Csource%2Cupn%2Cexpire&lmt=1400256356957873&ei=mBz2WM_RO4SrcuSgkJgP&initcwndbps=7396250&signature=2F1D1100B74FD8EF2A7A695DFF16BE7855C27E93.0D6B4A07856414AFE6A90533953CF67CA2D1A909&dur=5.523&key=yt6&upn=JTvgBlGnIAU&keepalive=yes&itag=171&clen=92875&ratebypass=yes", "filesize": 92875, "vcodec": "none", "format_note": "DASH audio", "abr": 128, "player_url": null, "ext": "webm", "preference": -50, "fps": 1, "format_id": "171", "acodec": "vorbis"}, {"http_headers": {"Accept-Charset": "ISO-8859-1,utf-8;q=0.7,*;q=0.7", "Accept-Language": "en-us,en;q=0.5", "Accept-Encoding": "gzip, deflate", "Accept": "text/html,application/xhtml+xml,application/xml;q=0.9,*/*;q=0.8", "User-Agent": "Mozilla/5.0 (X11; Linux x86_64; rv:10.0) Gecko/20150101 Firefox/47.0 (Chrome)"}, "tbr": 52.591, "container": "webm", "format": "278 - 256x144 (144p)", "url": "https://r1---sn-5jvoxu-8pxe.googlevideo.com/videoplayback?mime=video%2Fwebm&ip=138.232.125.82&requiressl=yes&mm=31&source=youtube&pl=16&mn=sn-5jvoxu-8pxe&ipbits=0&mt=1492524097&mv=m&id=o-APL3vFNNdf9glAigF87X04wArd6xkPg5cmajUkNlumu3&ms=au&expire=1492545785&gir=yes&sparams=clen%2Cdur%2Cei%2Cgir%2Cid%2Cinitcwndbps%2Cip%2Cipbits%2Citag%2Ckeepalive%2Clmt%2Cmime%2Cmm%2Cmn%2Cms%2Cmv%2Cpl%2Crequiressl%2Csource%2Cupn%2Cexpire&lmt=1400256391796247&ei=mBz2WM_RO4SrcuSgkJgP&initcwndbps=7396250&signature=2253F5DF3CEC472204FBD207E6C5E1EB445E4F64.22412A39240BC9133599B05C382C09F5A5BEE78E&dur=5.520&key=yt6&upn=JTvgBlGnIAU&keepalive=yes&itag=278&clen=36288&ratebypass=yes", "vcodec": "vp9", "format_note": "144p", "player_url": null, "width": 256, "ext": "webm", "preference": -40, "fps": 1, "acodec": "none", "protocol": "https", "format_id": "278", "height": 144, "filesize": 36288}, {"asr": null, "tbr": 113, "protocol": "https", "format": "160 - 256x144 (DASH video)", "format_note": "DASH video", "height": 144, "preference": -40, "manifest_url": "https://manifest.googlevideo.com/api/manifest/dash/expire/1492545785/pl/16/as/fmp4_audio_clear%2Cfmp4_sd_hd_clear/ei/mRz2WI-5IIGncLCDhNAP/id/o-AJfpOJIZRd4guGqLVZo5YFEVFfZIbjjwJLEK85KKX_CK/upn/56r6CoC9ww0/initcwndbps/7396250/sparams/as%2Cei%2Chfr%2Cid%2Cinitcwndbps%2Cip%2Cipbits%2Citag%2Cmm%2Cmn%2Cms%2Cmv%2Cpl%2Cplayback_host%2Crequiressl%2Csource%2Cexpire/ip/138.232.125.82/signature/E43235ACE6B2AD6546BC00213957D21D96561B67.CED53CE71D11AD2C16E24BA0236F96C4CCE98958/source/youtube/ms/au/playback_host/r1---sn-5jvoxu-8pxe.googlevideo.com/mt/1492524097/mv/m/mm/31/mn/sn-5jvoxu-8pxe/requiressl/yes/key/yt6/itag/0/ipbits/0/hfr/1", "format_id": "160", "language": null, "http_headers": {"Accept-Charset": "ISO-8859-1,utf-8;q=0.7,*;q=0.7", "Accept-Language": "en-us,en;q=0.5", "Accept-Encoding": "gzip, deflate", "Accept": "text/html,application/xhtml+xml,application/xml;q=0.9,*/*;q=0.8", "User-Agent": "Mozilla/5.0 (X11; Linux x86_64; rv:10.0) Gecko/20150101 Firefox/47.0 (Chrome)"}, "url": "https://r1---sn-5jvoxu-8pxe.googlevideo.com/videoplayback?id=59f495938e0ad3ab&itag=160&source=youtube&requiressl=yes&pl=16&ei=mRz2WI-5IIGncLCDhNAP&initcwndbps=7396250&ms=au&mv=m&mm=31&mn=sn-5jvoxu-8pxe&ratebypass=yes&mime=video/mp4&gir=yes&clen=78028&lmt=1388018136406302&dur=5.480&upn=56r6CoC9ww0&signature=6CC80F02474F12ED0856C580BB749F327E984DE3.86D203672D37BE55ED362D6CB51D5C49FFBBAAA9&mt=1492524097&key=dg_yt0&ip=138.232.125.82&ipbits=0&expire=1492545785&sparams=ip,ipbits,expire,id,itag,source,requiressl,pl,ei,initcwndbps,ms,mv,mm,mn,ratebypass,mime,gir,clen,lmt,dur", "vcodec": "avc1.4d400c", "width": 256, "ext": "mp4", "filesize": 78028, "fps": 15, "acodec": "none"}, {"http_headers": {"Accept-Charset": "ISO-8859-1,utf-8;q=0.7,*;q=0.7", "Accept-Language": "en-us,en;q=0.5", "Accept-Encoding": "gzip, deflate", "Accept": "text/html,application/xhtml+xml,application/xml;q=0.9,*/*;q=0.8", "User-Agent": "Mozilla/5.0 (X11; Linux x86_64; rv:10.0) Gecko/20150101 Firefox/47.0 (Chrome)"}, "tbr": 127.867, "protocol": "https", "format": "242 - 426x240 (240p)", "url": "https://r1---sn-5jvoxu-8pxe.googlevideo.com/videoplayback?mime=video%2Fwebm&ip=138.232.125.82&requiressl=yes&mm=31&source=youtube&pl=16&mn=sn-5jvoxu-8pxe&ipbits=0&mt=1492524097&mv=m&id=o-APL3vFNNdf9glAigF87X04wArd6xkPg5cmajUkNlumu3&ms=au&expire=1492545785&gir=yes&sparams=clen%2Cdur%2Cei%2Cgir%2Cid%2Cinitcwndbps%2Cip%2Cipbits%2Citag%2Ckeepalive%2Clmt%2Cmime%2Cmm%2Cmn%2Cms%2Cmv%2Cpl%2Crequiressl%2Csource%2Cupn%2Cexpire&lmt=1400256382963208&ei=mBz2WM_RO4SrcuSgkJgP&initcwndbps=7396250&signature=E42B4AFDBF44ABFB8AA4E47B2AD13B5FC2B46B6F.3C70DA5F332BAC0EBB06895204A951E804EDC024&dur=5.480&key=yt6&upn=JTvgBlGnIAU&keepalive=yes&itag=242&clen=87589&ratebypass=yes", "vcodec": "vp9", "format_note": "240p", "player_url": null, "width": 426, "ext": "webm", "preference": -40, "fps": 1, "acodec": "none", "format_id": "242", "height": 240, "filesize": 87589}, {"http_headers": {"Accept-Charset": "ISO-8859-1,utf-8;q=0.7,*;q=0.7", "Accept-Language": "en-us,en;q=0.5", "Accept-Encoding": "gzip, deflate", "Accept": "text/html,application/xhtml+xml,application/xml;q=0.9,*/*;q=0.8", "User-Agent": "Mozilla/5.0 (X11; Linux x86_64; rv:10.0) Gecko/20150101 Firefox/47.0 (Chrome)"}, "tbr": 222.817, "protocol": "https", "format": "243 - 640x360 (360p)", "url": "https://r1---sn-5jvoxu-8pxe.googlevideo.com/videoplayback?mime=video%2Fwebm&ip=138.232.125.82&requiressl=yes&mm=31&source=youtube&pl=16&mn=sn-5jvoxu-8pxe&ipbits=0&mt=1492524097&mv=m&id=o-APL3vFNNdf9glAigF87X04wArd6xkPg5cmajUkNlumu3&ms=au&expire=1492545785&gir=yes&sparams=clen%2Cdur%2Cei%2Cgir%2Cid%2Cinitcwndbps%2Cip%2Cipbits%2Citag%2Ckeepalive%2Clmt%2Cmime%2Cmm%2Cmn%2Cms%2Cmv%2Cpl%2Crequiressl%2Csource%2Cupn%2Cexpire&lmt=1400256391439261&ei=mBz2WM_RO4SrcuSgkJgP&initcwndbps=7396250&signature=A16CFAABBB3D991C907D3BB650DD13C629F33C72.5836F9EB228DFD295FA2EE8AAE39D566183DCA25&dur=5.480&key=yt6&upn=JTvgBlGnIAU&keepalive=yes&itag=243&clen=152630&ratebypass=yes", "vcodec": "vp9", "format_note": "360p", "player_url": null, "width": 640, "ext": "webm", "preference": -40, "fps": 1, "acodec": "none", "format_id": "243", "height": 360, "filesize": 152630}, {"asr": null, "tbr": 246, "protocol": "https", "format": "133 - 426x240 (DASH video)", "format_note": "DASH video", "height": 240, "preference": -40, "manifest_url": "https://manifest.googlevideo.com/api/manifest/dash/expire/1492545785/pl/16/as/fmp4_audio_clear%2Cfmp4_sd_hd_clear/ei/mRz2WI-5IIGncLCDhNAP/id/o-AJfpOJIZRd4guGqLVZo5YFEVFfZIbjjwJLEK85KKX_CK/upn/56r6CoC9ww0/initcwndbps/7396250/sparams/as%2Cei%2Chfr%2Cid%2Cinitcwndbps%2Cip%2Cipbits%2Citag%2Cmm%2Cmn%2Cms%2Cmv%2Cpl%2Cplayback_host%2Crequiressl%2Csource%2Cexpire/ip/138.232.125.82/signature/E43235ACE6B2AD6546BC00213957D21D96561B67.CED53CE71D11AD2C16E24BA0236F96C4CCE98958/source/youtube/ms/au/playback_host/r1---sn-5jvoxu-8pxe.googlevideo.com/mt/1492524097/mv/m/mm/31/mn/sn-5jvoxu-8pxe/requiressl/yes/key/yt6/itag/0/ipbits/0/hfr/1", "format_id": "133", "language": null, "http_headers": {"Accept-Charset": "ISO-8859-1,utf-8;q=0.7,*;q=0.7", "Accept-Language": "en-us,en;q=0.5", "Accept-Encoding": "gzip, deflate", "Accept": "text/html,application/xhtml+xml,application/xml;q=0.9,*/*;q=0.8", "User-Agent": "Mozilla/5.0 (X11; Linux x86_64; rv:10.0) Gecko/20150101 Firefox/47.0 (Chrome)"}, "url": "https://r1---sn-5jvoxu-8pxe.googlevideo.com/videoplayback?id=59f495938e0ad3ab&itag=133&source=youtube&requiressl=yes&pl=16&ei=mRz2WI-5IIGncLCDhNAP&initcwndbps=7396250&ms=au&mv=m&mm=31&mn=sn-5jvoxu-8pxe&ratebypass=yes&mime=video/mp4&gir=yes&clen=168764&lmt=1388018139404613&dur=5.480&upn=56r6CoC9ww0&signature=64A80ABC151DC16D0CB5B6F271F8350CECACE72F.8827FE488F53FF2D1F90BB3C86C4E3C5AAB0A1F1&mt=1492524097&key=dg_yt0&ip=138.232.125.82&ipbits=0&expire=1492545785&sparams=ip,ipbits,expire,id,itag,source,requiressl,pl,ei,initcwndbps,ms,mv,mm,mn,ratebypass,mime,gir,clen,lmt,dur", "vcodec": "avc1.4d4015", "width": 426, "ext": "mp4", "filesize": 168764, "fps": 25, "acodec": "none"}, {"asr": null, "tbr": 352, "protocol": "https", "format": "134 - 640x360 (DASH video)", "format_note": "DASH video", "height": 360, "preference": -40, "manifest_url": "https://manifest.googlevideo.com/api/manifest/dash/expire/1492545785/pl/16/as/fmp4_audio_clear%2Cfmp4_sd_hd_clear/ei/mRz2WI-5IIGncLCDhNAP/id/o-AJfpOJIZRd4guGqLVZo5YFEVFfZIbjjwJLEK85KKX_CK/upn/56r6CoC9ww0/initcwndbps/7396250/sparams/as%2Cei%2Chfr%2Cid%2Cinitcwndbps%2Cip%2Cipbits%2Citag%2Cmm%2Cmn%2Cms%2Cmv%2Cpl%2Cplayback_host%2Crequiressl%2Csource%2Cexpire/ip/138.232.125.82/signature/E43235ACE6B2AD6546BC00213957D21D96561B67.CED53CE71D11AD2C16E24BA0236F96C4CCE98958/source/youtube/ms/au/playback_host/r1---sn-5jvoxu-8pxe.googlevideo.com/mt/1492524097/mv/m/mm/31/mn/sn-5jvoxu-8pxe/requiressl/yes/key/yt6/itag/0/ipbits/0/hfr/1", "format_id": "134", "language": null, "http_headers": {"Accept-Charset": "ISO-8859-1,utf-8;q=0.7,*;q=0.7", "Accept-Language": "en-us,en;q=0.5", "Accept-Encoding": "gzip, deflate", "Accept": "text/html,application/xhtml+xml,application/xml;q=0.9,*/*;q=0.8", "User-Agent": "Mozilla/5.0 (X11; Linux x86_64; rv:10.0) Gecko/20150101 Firefox/47.0 (Chrome)"}, "url": "https://r1---sn-5jvoxu-8pxe.googlevideo.com/videoplayback?id=59f495938e0ad3ab&itag=134&source=youtube&requiressl=yes&pl=16&ei=mRz2WI-5IIGncLCDhNAP&initcwndbps=7396250&ms=au&mv=m&mm=31&mn=sn-5jvoxu-8pxe&ratebypass=yes&mime=video/mp4&gir=yes&clen=241745&lmt=1388018143401153&dur=5.480&upn=56r6CoC9ww0&signature=37C63E1E9EC50E04C61DE2D82776931C0E6AEAA5.8E59244ABAD5C10A37BB08E2C4EF344CE0BC4C3D&mt=1492524097&key=dg_yt0&ip=138.232.125.82&ipbits=0&expire=1492545785&sparams=ip,ipbits,expire,id,itag,source,requiressl,pl,ei,initcwndbps,ms,mv,mm,mn,ratebypass,mime,gir,clen,lmt,dur", "vcodec": "avc1.4d401e", "width": 640, "ext": "mp4", "filesize": 241745, "fps": 25, "acodec": "none"}, {"http_headers": {"Accept-Charset": "ISO-8859-1,utf-8;q=0.7,*;q=0.7", "Accept-Language": "en-us,en;q=0.5", "Accept-Encoding": "gzip, deflate", "Accept": "text/html,application/xhtml+xml,application/xml;q=0.9,*/*;q=0.8", "User-Agent": "Mozilla/5.0 (X11; Linux x86_64; rv:10.0) Gecko/20150101 Firefox/47.0 (Chrome)"}, "tbr": 405.592, "protocol": "https", "format": "244 - 854x480 (480p)", "url": "https://r1---sn-5jvoxu-8pxe.googlevideo.com/videoplayback?mime=video%2Fwebm&ip=138.232.125.82&requiressl=yes&mm=31&source=youtube&pl=16&mn=sn-5jvoxu-8pxe&ipbits=0&mt=1492524097&mv=m&id=o-APL3vFNNdf9glAigF87X04wArd6xkPg5cmajUkNlumu3&ms=au&expire=1492545785&gir=yes&sparams=clen%2Cdur%2Cei%2Cgir%2Cid%2Cinitcwndbps%2Cip%2Cipbits%2Citag%2Ckeepalive%2Clmt%2Cmime%2Cmm%2Cmn%2Cms%2Cmv%2Cpl%2Crequiressl%2Csource%2Cupn%2Cexpire&lmt=1400256403699803&ei=mBz2WM_RO4SrcuSgkJgP&initcwndbps=7396250&signature=0D0942AE415E4545B0AD17BA8B0EB6A1532AD4ED.4E24578812EC599117305DC9885CC1237924B444&dur=5.480&key=yt6&upn=JTvgBlGnIAU&keepalive=yes&itag=244&clen=277831&ratebypass=yes", "vcodec": "vp9", "format_note": "480p", "player_url": null, "width": 854, "ext": "webm", "preference": -40, "fps": 1, "acodec": "none", "format_id": "244", "height": 480, "filesize": 277831}, {"asr": null, "tbr": 602, "protocol": "https", "format": "135 - 854x480 (DASH video)", "format_note": "DASH video", "height": 480, "preference": -40, "manifest_url": "https://manifest.googlevideo.com/api/manifest/dash/expire/1492545785/pl/16/as/fmp4_audio_clear%2Cfmp4_sd_hd_clear/ei/mRz2WI-5IIGncLCDhNAP/id/o-AJfpOJIZRd4guGqLVZo5YFEVFfZIbjjwJLEK85KKX_CK/upn/56r6CoC9ww0/initcwndbps/7396250/sparams/as%2Cei%2Chfr%2Cid%2Cinitcwndbps%2Cip%2Cipbits%2Citag%2Cmm%2Cmn%2Cms%2Cmv%2Cpl%2Cplayback_host%2Crequiressl%2Csource%2Cexpire/ip/138.232.125.82/signature/E43235ACE6B2AD6546BC00213957D21D96561B67.CED53CE71D11AD2C16E24BA0236F96C4CCE98958/source/youtube/ms/au/playback_host/r1---sn-5jvoxu-8pxe.googlevideo.com/mt/1492524097/mv/m/mm/31/mn/sn-5jvoxu-8pxe/requiressl/yes/key/yt6/itag/0/ipbits/0/hfr/1", "format_id": "135", "language": null, "http_headers": {"Accept-Charset": "ISO-8859-1,utf-8;q=0.7,*;q=0.7", "Accept-Language": "en-us,en;q=0.5", "Accept-Encoding": "gzip, deflate", "Accept": "text/html,application/xhtml+xml,application/xml;q=0.9,*/*;q=0.8", "User-Agent": "Mozilla/5.0 (X11; Linux x86_64; rv:10.0) Gecko/20150101 Firefox/47.0 (Chrome)"}, "url": "https://r1---sn-5jvoxu-8pxe.googlevideo.com/videoplayback?id=59f495938e0ad3ab&itag=135&source=youtube&requiressl=yes&pl=16&ei=mRz2WI-5IIGncLCDhNAP&initcwndbps=7396250&ms=au&mv=m&mm=31&mn=sn-5jvoxu-8pxe&ratebypass=yes&mime=video/mp4&gir=yes&clen=413018&lmt=1388018164397956&dur=5.480&upn=56r6CoC9ww0&signature=2BEAD9F413D1868F7A13FC4241BB73D2D2BC12BE.20EE8E6BD7245D7DF5B739F78759D1C8F9BBDDF4&mt=1492524097&key=dg_yt0&ip=138.232.125.82&ipbits=0&expire=1492545785&sparams=ip,ipbits,expire,id,itag,source,requiressl,pl,ei,initcwndbps,ms,mv,mm,mn,ratebypass,mime,gir,clen,lmt,dur", "vcodec": "avc1.4d401e", "width": 854, "ext": "mp4", "filesize": 413018, "fps": 25, "acodec": "none"}, {"http_headers": {"Accept-Charset": "ISO-8859-1,utf-8;q=0.7,*;q=0.7", "Accept-Language": "en-us,en;q=0.5", "Accept-Encoding": "gzip, deflate", "Accept": "text/html,application/xhtml+xml,application/xml;q=0.9,*/*;q=0.8", "User-Agent": "Mozilla/5.0 (X11; Linux x86_64; rv:10.0) Gecko/20150101 Firefox/47.0 (Chrome)"}, "tbr": 809.097, "protocol": "https", "format": "247 - 1280x720 (720p)", "url": "https://r1---sn-5jvoxu-8pxe.googlevideo.com/videoplayback?mime=video%2Fwebm&ip=138.232.125.82&requiressl=yes&mm=31&source=youtube&pl=16&mn=sn-5jvoxu-8pxe&ipbits=0&mt=1492524097&mv=m&id=o-APL3vFNNdf9glAigF87X04wArd6xkPg5cmajUkNlumu3&ms=au&expire=1492545785&gir=yes&sparams=clen%2Cdur%2Cei%2Cgir%2Cid%2Cinitcwndbps%2Cip%2Cipbits%2Citag%2Ckeepalive%2Clmt%2Cmime%2Cmm%2Cmn%2Cms%2Cmv%2Cpl%2Crequiressl%2Csource%2Cupn%2Cexpire&lmt=1400256426481640&ei=mBz2WM_RO4SrcuSgkJgP&initcwndbps=7396250&signature=B87EAC2457362E3B611D47425A007D92C7CC8396.385CAC0FA5FBF68F669F8A3FFCFB7F6CBC1B2504&dur=5.480&key=yt6&upn=JTvgBlGnIAU&keepalive=yes&itag=247&clen=554232&ratebypass=yes", "vcodec": "vp9", "format_note": "720p", "player_url": null, "width": 1280, "ext": "webm", "preference": -40, "fps": 1, "acodec": "none", "format_id": "247", "height": 720, "filesize": 554232}, {"asr": null, "tbr": 1003, "protocol": "https", "format": "136 - 1280x720 (DASH video)", "format_note": "DASH video", "height": 720, "preference": -40, "manifest_url": "https://manifest.googlevideo.com/api/manifest/dash/expire/1492545785/pl/16/as/fmp4_audio_clear%2Cfmp4_sd_hd_clear/ei/mRz2WI-5IIGncLCDhNAP/id/o-AJfpOJIZRd4guGqLVZo5YFEVFfZIbjjwJLEK85KKX_CK/upn/56r6CoC9ww0/initcwndbps/7396250/sparams/as%2Cei%2Chfr%2Cid%2Cinitcwndbps%2Cip%2Cipbits%2Citag%2Cmm%2Cmn%2Cms%2Cmv%2Cpl%2Cplayback_host%2Crequiressl%2Csource%2Cexpire/ip/138.232.125.82/signature/E43235ACE6B2AD6546BC00213957D21D96561B67.CED53CE71D11AD2C16E24BA0236F96C4CCE98958/source/youtube/ms/au/playback_host/r1---sn-5jvoxu-8pxe.googlevideo.com/mt/1492524097/mv/m/mm/31/mn/sn-5jvoxu-8pxe/requiressl/yes/key/yt6/itag/0/ipbits/0/hfr/1", "format_id": "136", "language": null, "http_headers": {"Accept-Charset": "ISO-8859-1,utf-8;q=0.7,*;q=0.7", "Accept-Language": "en-us,en;q=0.5", "Accept-Encoding": "gzip, deflate", "Accept": "text/html,application/xhtml+xml,application/xml;q=0.9,*/*;q=0.8", "User-Agent": "Mozilla/5.0 (X11; Linux x86_64; rv:10.0) Gecko/20150101 Firefox/47.0 (Chrome)"}, "url": "https://r1---sn-5jvoxu-8pxe.googlevideo.com/videoplayback?id=59f495938e0ad3ab&itag=136&source=youtube&requiressl=yes&pl=16&ei=mRz2WI-5IIGncLCDhNAP&initcwndbps=7396250&ms=au&mv=m&mm=31&mn=sn-5jvoxu-8pxe&ratebypass=yes&mime=video/mp4&gir=yes&clen=687690&lmt=1388018162469247&dur=5.480&upn=56r6CoC9ww0&signature=2A91722F24AE39CACF6D52B657709DC9BDAC2145.714EEEF9BEBDEAB8D1AF1BFA8A7108899B53721E&mt=1492524097&key=dg_yt0&ip=138.232.125.82&ipbits=0&expire=1492545785&sparams=ip,ipbits,expire,id,itag,source,requiressl,pl,ei,initcwndbps,ms,mv,mm,mn,ratebypass,mime,gir,clen,lmt,dur", "vcodec": "avc1.4d401f", "width": 1280, "ext": "mp4", "filesize": 687690, "fps": 25, "acodec": "none"}, {"http_headers": {"Accept-Charset": "ISO-8859-1,utf-8;q=0.7,*;q=0.7", "Accept-Language": "en-us,en;q=0.5", "Accept-Encoding": "gzip, deflate", "Accept": "text/html,application/xhtml+xml,application/xml;q=0.9,*/*;q=0.8", "User-Agent": "Mozilla/5.0 (X11; Linux x86_64; rv:10.0) Gecko/20150101 Firefox/47.0 (Chrome)"}, "tbr": 1351.697, "protocol": "https", "format": "248 - 1920x1080 (1080p)", "url": "https://r1---sn-5jvoxu-8pxe.googlevideo.com/videoplayback?mime=video%2Fwebm&ip=138.232.125.82&requiressl=yes&mm=31&source=youtube&pl=16&mn=sn-5jvoxu-8pxe&ipbits=0&mt=1492524097&mv=m&id=o-APL3vFNNdf9glAigF87X04wArd6xkPg5cmajUkNlumu3&ms=au&expire=1492545785&gir=yes&sparams=clen%2Cdur%2Cei%2Cgir%2Cid%2Cinitcwndbps%2Cip%2Cipbits%2Citag%2Ckeepalive%2Clmt%2Cmime%2Cmm%2Cmn%2Cms%2Cmv%2Cpl%2Crequiressl%2Csource%2Cupn%2Cexpire&lmt=1400256836344460&ei=mBz2WM_RO4SrcuSgkJgP&initcwndbps=7396250&signature=A5BB277F2D0E569628344FD140AE8368CB97F41A.7F07428117921EAE3CF8B9166014E57522EB0706&dur=5.480&key=yt6&upn=JTvgBlGnIAU&keepalive=yes&itag=248&clen=925913&ratebypass=yes", "vcodec": "vp9", "format_note": "1080p", "player_url": null, "width": 1920, "ext": "webm", "preference": -40, "fps": 1, "acodec": "none", "format_id": "248", "height": 1080, "filesize": 925913}, {"asr": null, "tbr": 1896, "protocol": "https", "format": "137 - 1920x1080 (DASH video)", "format_note": "DASH video", "height": 1080, "preference": -40, "manifest_url": "https://manifest.googlevideo.com/api/manifest/dash/expire/1492545785/pl/16/as/fmp4_audio_clear%2Cfmp4_sd_hd_clear/ei/mRz2WI-5IIGncLCDhNAP/id/o-AJfpOJIZRd4guGqLVZo5YFEVFfZIbjjwJLEK85KKX_CK/upn/56r6CoC9ww0/initcwndbps/7396250/sparams/as%2Cei%2Chfr%2Cid%2Cinitcwndbps%2Cip%2Cipbits%2Citag%2Cmm%2Cmn%2Cms%2Cmv%2Cpl%2Cplayback_host%2Crequiressl%2Csource%2Cexpire/ip/138.232.125.82/signature/E43235ACE6B2AD6546BC00213957D21D96561B67.CED53CE71D11AD2C16E24BA0236F96C4CCE98958/source/youtube/ms/au/playback_host/r1---sn-5jvoxu-8pxe.googlevideo.com/mt/1492524097/mv/m/mm/31/mn/sn-5jvoxu-8pxe/requiressl/yes/key/yt6/itag/0/ipbits/0/hfr/1", "format_id": "137", "language": null, "http_headers": {"Accept-Charset": "ISO-8859-1,utf-8;q=0.7,*;q=0.7", "Accept-Language": "en-us,en;q=0.5", "Accept-Encoding": "gzip, deflate", "Accept": "text/html,application/xhtml+xml,application/xml;q=0.9,*/*;q=0.8", "User-Agent": "Mozilla/5.0 (X11; Linux x86_64; rv:10.0) Gecko/20150101 Firefox/47.0 (Chrome)"}, "url": "https://r1---sn-5jvoxu-8pxe.googlevideo.com/videoplayback?id=59f495938e0ad3ab&itag=137&source=youtube&requiressl=yes&pl=16&ei=mRz2WI-5IIGncLCDhNAP&initcwndbps=7396250&ms=au&mv=m&mm=31&mn=sn-5jvoxu-8pxe&ratebypass=yes&mime=video/mp4&gir=yes&clen=1299376&lmt=1388018182465446&dur=5.480&upn=56r6CoC9ww0&signature=76D35ED936AF50FA7395C6D7C69947716351253A.188F555E2049494885B709BBC34E7F7F81504383&mt=1492524097&key=dg_yt0&ip=138.232.125.82&ipbits=0&expire=1492545785&sparams=ip,ipbits,expire,id,itag,source,requiressl,pl,ei,initcwndbps,ms,mv,mm,mn,ratebypass,mime,gir,clen,lmt,dur", "vcodec": "avc1.640028", "width": 1920, "ext": "mp4", "filesize": 1299376, "fps": 25, "acodec": "none"}, {"http_headers": {"Accept-Charset": "ISO-8859-1,utf-8;q=0.7,*;q=0.7", "Accept-Language": "en-us,en;q=0.5", "Accept-Encoding": "gzip, deflate", "Accept": "text/html,application/xhtml+xml,application/xml;q=0.9,*/*;q=0.8", "User-Agent": "Mozilla/5.0 (X11; Linux x86_64; rv:10.0) Gecko/20150101 Firefox/47.0 (Chrome)"}, "protocol": "https", "format": "17 - 176x144 (small)", "url": "https://r1---sn-5jvoxu-8pxe.googlevideo.com/videoplayback?mime=video%2F3gpp&ip=138.232.125.82&requiressl=yes&mm=31&source=youtube&pl=16&mn=sn-5jvoxu-8pxe&mt=1492524097&mv=m&id=o-APL3vFNNdf9glAigF87X04wArd6xkPg5cmajUkNlumu3&ms=au&expire=1492545785&gir=yes&sparams=clen%2Cdur%2Cei%2Cgir%2Cid%2Cinitcwndbps%2Cip%2Cipbits%2Citag%2Clmt%2Cmime%2Cmm%2Cmn%2Cms%2Cmv%2Cpl%2Crequiressl%2Csource%2Cupn%2Cexpire&lmt=1388018120418656&ei=mBz2WM_RO4SrcuSgkJgP&initcwndbps=7396250&signature=90F5D4C162AA8C37BA0CEC0B33D2F93A7AE30FF9.53ABF0EA4F51E4989969F9C57B0444B4510624B7&dur=5.897&key=yt6&upn=JTvgBlGnIAU&ipbits=0&itag=17&clen=57748&ratebypass=yes", "vcodec": "mp4v.20.3", "format_note": "small", "ext": "3gp", "player_url": null, "width": 176, "abr": 24, "format_id": "17", "height": 144, "resolution": "176x144", "acodec": " mp4a.40.2"}, {"http_headers": {"Accept-Charset": "ISO-8859-1,utf-8;q=0.7,*;q=0.7", "Accept-Language": "en-us,en;q=0.5", "Accept-Encoding": "gzip, deflate", "Accept": "text/html,application/xhtml+xml,application/xml;q=0.9,*/*;q=0.8", "User-Agent": "Mozilla/5.0 (X11; Linux x86_64; rv:10.0) Gecko/20150101 Firefox/47.0 (Chrome)"}, "protocol": "https", "format": "36 - 320x180 (small)", "url": "https://r1---sn-5jvoxu-8pxe.googlevideo.com/videoplayback?mime=video%2F3gpp&ip=138.232.125.82&requiressl=yes&mm=31&source=youtube&pl=16&mn=sn-5jvoxu-8pxe&mt=1492524097&mv=m&id=o-APL3vFNNdf9glAigF87X04wArd6xkPg5cmajUkNlumu3&ms=au&expire=1492545785&gir=yes&sparams=clen%2Cdur%2Cei%2Cgir%2Cid%2Cinitcwndbps%2Cip%2Cipbits%2Citag%2Clmt%2Cmime%2Cmm%2Cmn%2Cms%2Cmv%2Cpl%2Crequiressl%2Csource%2Cupn%2Cexpire&lmt=1388018120422719&ei=mBz2WM_RO4SrcuSgkJgP&initcwndbps=7396250&signature=20FF4A4644E7BFF01ABAE5E1021EBD6E1384C7EC.5A8994532410142E17E0EE89527FA9F636C12681&dur=5.712&key=yt6&upn=JTvgBlGnIAU&ipbits=0&itag=36&clen=150390&ratebypass=yes", "vcodec": "mp4v.20.3", "format_note": "small", "height": 180, "width": 320, "ext": "3gp", "format_id": "36", "player_url": null, "resolution": "320x180", "acodec": " mp4a.40.2"}, {"http_headers": {"Accept-Charset": "ISO-8859-1,utf-8;q=0.7,*;q=0.7", "Accept-Language": "en-us,en;q=0.5", "Accept-Encoding": "gzip, deflate", "Accept": "text/html,application/xhtml+xml,application/xml;q=0.9,*/*;q=0.8", "User-Agent": "Mozilla/5.0 (X11; Linux x86_64; rv:10.0) Gecko/20150101 Firefox/47.0 (Chrome)"}, "protocol": "https", "format": "43 - 640x360 (medium)", "url": "https://r1---sn-5jvoxu-8pxe.googlevideo.com/videoplayback?mime=video%2Fwebm&ip=138.232.125.82&requiressl=yes&mm=31&source=youtube&pl=16&mn=sn-5jvoxu-8pxe&mt=1492524097&mv=m&id=o-APL3vFNNdf9glAigF87X04wArd6xkPg5cmajUkNlumu3&ms=au&expire=1492545785&gir=yes&sparams=clen%2Cdur%2Cei%2Cgir%2Cid%2Cinitcwndbps%2Cip%2Cipbits%2Citag%2Clmt%2Cmime%2Cmm%2Cmn%2Cms%2Cmv%2Cpl%2Cratebypass%2Crequiressl%2Csource%2Cupn%2Cexpire&lmt=1358356191065019&ei=mBz2WM_RO4SrcuSgkJgP&initcwndbps=7396250&signature=D004B5B266C5572BFC98D89DDABC723EE00C6C2B.851655F94AB12E99CCA8A96980B5A8541D84598A&dur=0.000&key=yt6&upn=JTvgBlGnIAU&ratebypass=yes&ipbits=0&itag=43&clen=457245", "vcodec": "vp8.0", "format_note": "medium", "ext": "webm", "player_url": null, "width": 640, "abr": 128, "format_id": "43", "height": 360, "resolution": "640x360", "acodec": " vorbis"}, {"http_headers": {"Accept-Charset": "ISO-8859-1,utf-8;q=0.7,*;q=0.7", "Accept-Language": "en-us,en;q=0.5", "Accept-Encoding": "gzip, deflate", "Accept": "text/html,application/xhtml+xml,application/xml;q=0.9,*/*;q=0.8", "User-Agent": "Mozilla/5.0 (X11; Linux x86_64; rv:10.0) Gecko/20150101 Firefox/47.0 (Chrome)"}, "protocol": "https", "format": "18 - 640x360 (medium)", "url": "https://r1---sn-5jvoxu-8pxe.googlevideo.com/videoplayback?mime=video%2Fmp4&ip=138.232.125.82&requiressl=yes&mm=31&source=youtube&pl=16&mn=sn-5jvoxu-8pxe&mt=1492524097&mv=m&id=o-APL3vFNNdf9glAigF87X04wArd6xkPg5cmajUkNlumu3&ms=au&expire=1492545785&gir=yes&sparams=clen%2Cdur%2Cei%2Cgir%2Cid%2Cinitcwndbps%2Cip%2Cipbits%2Citag%2Clmt%2Cmime%2Cmm%2Cmn%2Cms%2Cmv%2Cpl%2Cratebypass%2Crequiressl%2Csource%2Cupn%2Cexpire&lmt=1388018149398821&ei=mBz2WM_RO4SrcuSgkJgP&initcwndbps=7396250&signature=CD444EAC5DC1BD65FECCB6A485A77AA4A28A62A4.2443782B6885CD6CA27946B6B6BD21A3BE24704D&dur=5.572&key=yt6&upn=JTvgBlGnIAU&ratebypass=yes&ipbits=0&itag=18&clen=455814", "vcodec": "avc1.42001E", "format_note": "medium", "ext": "mp4", "player_url": null, "width": 640, "abr": 96, "format_id": "18", "height": 360, "resolution": "640x360", "acodec": " mp4a.40.2"}, {"http_headers": {"Accept-Charset": "ISO-8859-1,utf-8;q=0.7,*;q=0.7", "Accept-Language": "en-us,en;q=0.5", "Accept-Encoding": "gzip, deflate", "Accept": "text/html,application/xhtml+xml,application/xml;q=0.9,*/*;q=0.8", "User-Agent": "Mozilla/5.0 (X11; Linux x86_64; rv:10.0) Gecko/20150101 Firefox/47.0 (Chrome)"}, "protocol": "https", "format": "22 - 1280x720 (hd720)", "url": "https://r1---sn-5jvoxu-8pxe.googlevideo.com/videoplayback?mime=video%2Fmp4&ip=138.232.125.82&requiressl=yes&mm=31&source=youtube&pl=16&mn=sn-5jvoxu-8pxe&mt=1492524097&mv=m&id=o-APL3vFNNdf9glAigF87X04wArd6xkPg5cmajUkNlumu3&ms=au&expire=1492545785&sparams=dur%2Cei%2Cid%2Cinitcwndbps%2Cip%2Cipbits%2Citag%2Clmt%2Cmime%2Cmm%2Cmn%2Cms%2Cmv%2Cpl%2Cratebypass%2Crequiressl%2Csource%2Cupn%2Cexpire&lmt=1471686036908707&ei=mBz2WM_RO4SrcuSgkJgP&initcwndbps=7396250&signature=1A7B9AF4A07C0461FE2B0C87DAFAE59CC2641853.31E57397BD080F93533E8708C5D963EB1BE8AAB4&dur=5.572&key=yt6&upn=JTvgBlGnIAU&ratebypass=yes&ipbits=0&itag=22", "vcodec": "avc1.64001F", "format_note": "hd720", "ext": "mp4", "player_url": null, "width": 1280, "abr": 192, "format_id": "22", "height": 720, "resolution": "1280x720", "acodec": " mp4a.40.2"}], "playlist_id": "PL2Ufja2qoGV5FNRNR7UR1r6P-Wd8B8RcE", "uploader": "LeFloid", "format_id": "137+171", "episode_number": null, "uploader_id": "LeFloid", "subtitles": {}, "playlist_title": "LeNEWS", "thumbnails": [{"url": "https://i.ytimg.com/vi/WfSVk44K06s/maxresdefault.jpg", "id": "0"}], "license": "Standard YouTube License", "alt_title": null, "age_limit": 0, "vcodec": "avc1.640028", "thumbnail": "https://i.ytimg.com/vi/WfSVk44K06s/maxresdefault.jpg", "vbr": null, "ext": "mp4", "extractor": "youtube", "end_time": null, "webpage_url": "https://www.youtube.com/watch?v=WfSVk44K06s", "extractor_key": "Youtube", "resolution": null, "width": 1920, "n_entries": 434}